<?xml version="1.0" encoding="UTF-8"?>
<export version="E">
  <design>
    <source>/home/timcaldwell/projects/sync_ope/hardware/sync_ope.kicad_sch</source>
    <date>Tue 23 Jan 2024 11:59:48</date>
    <tool>Eeschema 7.0.9</tool>
    <sheet number="1" name="/" tstamps="/">
      <title_block>
        <title>sync_ope</title>
        <company>based on circuit design -byGaël Jaton</company>
        <rev>1.0.1</rev>
        <date>2022-11-24</date>
        <source>sync_ope.kicad_sch</source>
        <comment number="1" value="updated by cyberboy666"/>
        <comment number="2" value=""/>
        <comment number="3" value=""/>
        <comment number="4" value=""/>
        <comment number="5" value=""/>
        <comment number="6" value=""/>
        <comment number="7" value=""/>
        <comment number="8" value=""/>
        <comment number="9" value=""/>
      </title_block>
    </sheet>
    <sheet number="2" name="/blanking/" tstamps="/00000000-0000-0000-0000-00005fdd6789/">
      <title_block>
        <title/>
        <company/>
        <rev/>
        <date/>
        <source>blanking.kicad_sch</source>
        <comment number="1" value=""/>
        <comment number="2" value=""/>
        <comment number="3" value=""/>
        <comment number="4" value=""/>
        <comment number="5" value=""/>
        <comment number="6" value=""/>
        <comment number="7" value=""/>
        <comment number="8" value=""/>
        <comment number="9" value=""/>
      </title_block>
    </sheet>
  </design>
  <components>
    <comp ref="C1">
      <value>220u</value>
      <footprint>Capacitor_THT:CP_Radial_D5.0mm_P2.50mm</footprint>
      <libsource lib="Sync-Ope-proto-rescue" part="CP_Small-Device" description=""/>
      <property name="Sheetname" value=""/>
      <property name="Sheetfile" value="sync_ope.kicad_sch"/>
      <sheetpath names="/" tstamps="/"/>
      <tstamps>00000000-0000-0000-0000-00005e27f84f</tstamps>
    </comp>
    <comp ref="C2">
      <value>2200u</value>
      <footprint>Capacitor_THT:CP_Radial_D13.0mm_P5.00mm</footprint>
      <libsource lib="Device" part="C_Polarized" description="Polarized capacitor"/>
      <property name="Sheetname" value=""/>
      <property name="Sheetfile" value="sync_ope.kicad_sch"/>
      <property name="ki_description" value="Polarized capacitor"/>
      <property name="ki_keywords" value="cap capacitor"/>
      <sheetpath names="/" tstamps="/"/>
      <tstamps>bc8d66ac-8db6-4304-b16d-cced9def3af1</tstamps>
    </comp>
    <comp ref="C3">
      <value>2200u</value>
      <footprint>Capacitor_THT:CP_Radial_D13.0mm_P5.00mm</footprint>
      <libsource lib="Device" part="C_Polarized" description="Polarized capacitor"/>
      <property name="Sheetname" value=""/>
      <property name="Sheetfile" value="sync_ope.kicad_sch"/>
      <property name="ki_description" value="Polarized capacitor"/>
      <property name="ki_keywords" value="cap capacitor"/>
      <sheetpath names="/" tstamps="/"/>
      <tstamps>3670c4d6-0ec9-4581-bae7-37b8509f96a5</tstamps>
    </comp>
    <comp ref="C4">
      <value>0.1u</value>
      <footprint>Capacitor_THT:C_Disc_D4.3mm_W1.9mm_P5.00mm</footprint>
      <libsource lib="Sync-Ope-proto-rescue" part="C-Device" description=""/>
      <property name="Sheetname" value=""/>
      <property name="Sheetfile" value="sync_ope.kicad_sch"/>
      <sheetpath names="/" tstamps="/"/>
      <tstamps>00000000-0000-0000-0000-00005dc4f328</tstamps>
    </comp>
    <comp ref="C10">
      <value>0.1u</value>
      <footprint>Capacitor_THT:C_Disc_D4.3mm_W1.9mm_P5.00mm</footprint>
      <libsource lib="Device" part="C_Small" description="Unpolarized capacitor, small symbol"/>
      <property name="Sheetname" value=""/>
      <property name="Sheetfile" value="sync_ope.kicad_sch"/>
      <property name="ki_description" value="Unpolarized capacitor, small symbol"/>
      <property name="ki_keywords" value="capacitor cap"/>
      <sheetpath names="/" tstamps="/"/>
      <tstamps>00000000-0000-0000-0000-000060edb0b5</tstamps>
    </comp>
    <comp ref="C11">
      <value>0.1u</value>
      <footprint>Capacitor_THT:C_Disc_D4.3mm_W1.9mm_P5.00mm</footprint>
      <libsource lib="Device" part="C_Small" description="Unpolarized capacitor, small symbol"/>
      <property name="Sheetname" value=""/>
      <property name="Sheetfile" value="sync_ope.kicad_sch"/>
      <property name="ki_description" value="Unpolarized capacitor, small symbol"/>
      <property name="ki_keywords" value="capacitor cap"/>
      <sheetpath names="/" tstamps="/"/>
      <tstamps>00000000-0000-0000-0000-000060f20911</tstamps>
    </comp>
    <comp ref="C12">
      <value>0.1u</value>
      <footprint>Capacitor_THT:C_Disc_D4.3mm_W1.9mm_P5.00mm</footprint>
      <libsource lib="Device" part="C_Small" description="Unpolarized capacitor, small symbol"/>
      <property name="Sheetname" value=""/>
      <property name="Sheetfile" value="sync_ope.kicad_sch"/>
      <property name="ki_description" value="Unpolarized capacitor, small symbol"/>
      <property name="ki_keywords" value="capacitor cap"/>
      <sheetpath names="/" tstamps="/"/>
      <tstamps>00000000-0000-0000-0000-000060f3962b</tstamps>
    </comp>
    <comp ref="C13">
      <value>0.1u</value>
      <footprint>Capacitor_THT:C_Disc_D4.3mm_W1.9mm_P5.00mm</footprint>
      <libsource lib="Device" part="C_Small" description="Unpolarized capacitor, small symbol"/>
      <property name="Sheetname" value=""/>
      <property name="Sheetfile" value="sync_ope.kicad_sch"/>
      <property name="ki_description" value="Unpolarized capacitor, small symbol"/>
      <property name="ki_keywords" value="capacitor cap"/>
      <sheetpath names="/" tstamps="/"/>
      <tstamps>00000000-0000-0000-0000-000060f3a3db</tstamps>
    </comp>
    <comp ref="C14">
      <value>0.1u</value>
      <footprint>Capacitor_THT:C_Disc_D4.3mm_W1.9mm_P5.00mm</footprint>
      <libsource lib="Device" part="C_Small" description="Unpolarized capacitor, small symbol"/>
      <property name="Sheetname" value=""/>
      <property name="Sheetfile" value="sync_ope.kicad_sch"/>
      <property name="ki_description" value="Unpolarized capacitor, small symbol"/>
      <property name="ki_keywords" value="capacitor cap"/>
      <sheetpath names="/" tstamps="/"/>
      <tstamps>00000000-0000-0000-0000-000060f8d5a5</tstamps>
    </comp>
    <comp ref="C15">
      <value>0.1u</value>
      <footprint>Capacitor_THT:C_Disc_D4.3mm_W1.9mm_P5.00mm</footprint>
      <libsource lib="Device" part="C_Small" description="Unpolarized capacitor, small symbol"/>
      <property name="Sheetname" value=""/>
      <property name="Sheetfile" value="sync_ope.kicad_sch"/>
      <property name="ki_description" value="Unpolarized capacitor, small symbol"/>
      <property name="ki_keywords" value="capacitor cap"/>
      <sheetpath names="/" tstamps="/"/>
      <tstamps>00000000-0000-0000-0000-000060f8dbde</tstamps>
    </comp>
    <comp ref="C16">
      <value>0.1u</value>
      <footprint>Capacitor_THT:C_Disc_D4.3mm_W1.9mm_P5.00mm</footprint>
      <libsource lib="Sync-Ope-proto-rescue" part="C-Sync-Ope-proto-Sync-Ope-proto-rescue" description=""/>
      <property name="Sheetname" value=""/>
      <property name="Sheetfile" value="sync_ope.kicad_sch"/>
      <sheetpath names="/" tstamps="/"/>
      <tstamps>00000000-0000-0000-0000-00005db9b36b</tstamps>
    </comp>
    <comp ref="C23">
      <value>0.1u</value>
      <footprint>Capacitor_THT:C_Disc_D4.3mm_W1.9mm_P5.00mm</footprint>
      <libsource lib="Device" part="C_Small" description="Unpolarized capacitor, small symbol"/>
      <property name="Sheetname" value=""/>
      <property name="Sheetfile" value="sync_ope.kicad_sch"/>
      <property name="ki_description" value="Unpolarized capacitor, small symbol"/>
      <property name="ki_keywords" value="capacitor cap"/>
      <sheetpath names="/" tstamps="/"/>
      <tstamps>00000000-0000-0000-0000-000061740cc0</tstamps>
    </comp>
    <comp ref="C24">
      <value>0.1u</value>
      <footprint>Capacitor_THT:C_Disc_D4.3mm_W1.9mm_P5.00mm</footprint>
      <libsource lib="Sync-Ope-proto-rescue" part="C-Device" description=""/>
      <property name="Sheetname" value=""/>
      <property name="Sheetfile" value="sync_ope.kicad_sch"/>
      <sheetpath names="/" tstamps="/"/>
      <tstamps>00000000-0000-0000-0000-000062477287</tstamps>
    </comp>
    <comp ref="C25">
      <value>0.1u</value>
      <footprint>Capacitor_THT:C_Disc_D4.3mm_W1.9mm_P5.00mm</footprint>
      <libsource lib="Device" part="C_Small" description="Unpolarized capacitor, small symbol"/>
      <property name="Sheetname" value=""/>
      <property name="Sheetfile" value="sync_ope.kicad_sch"/>
      <property name="ki_description" value="Unpolarized capacitor, small symbol"/>
      <property name="ki_keywords" value="capacitor cap"/>
      <sheetpath names="/" tstamps="/"/>
      <tstamps>00000000-0000-0000-0000-000062504cd0</tstamps>
    </comp>
    <comp ref="D1">
      <value>1n5819</value>
      <footprint>Diode_THT:D_DO-41_SOD81_P7.62mm_Horizontal</footprint>
      <libsource lib="Device" part="D_Schottky" description="Schottky diode"/>
      <property name="Sheetname" value=""/>
      <property name="Sheetfile" value="sync_ope.kicad_sch"/>
      <property name="ki_description" value="Schottky diode"/>
      <property name="ki_keywords" value="diode Schottky"/>
      <sheetpath names="/" tstamps="/"/>
      <tstamps>bf960921-d501-4d3d-a988-849edc839478</tstamps>
    </comp>
    <comp ref="D2">
      <value>1n5819</value>
      <footprint>Diode_THT:D_DO-41_SOD81_P7.62mm_Horizontal</footprint>
      <libsource lib="Device" part="D_Schottky" description="Schottky diode"/>
      <property name="Sheetname" value=""/>
      <property name="Sheetfile" value="sync_ope.kicad_sch"/>
      <property name="ki_description" value="Schottky diode"/>
      <property name="ki_keywords" value="diode Schottky"/>
      <sheetpath names="/" tstamps="/"/>
      <tstamps>415bca51-8b22-4605-acfd-a559d5f85385</tstamps>
    </comp>
    <comp ref="D3">
      <value>zener_1.8v</value>
      <footprint>Diode_THT:D_DO-35_SOD27_P7.62mm_Horizontal</footprint>
      <libsource lib="Sync-Ope-proto-rescue" part="D_Zener-Device" description=""/>
      <property name="Sheetname" value=""/>
      <property name="Sheetfile" value="sync_ope.kicad_sch"/>
      <sheetpath names="/" tstamps="/"/>
      <tstamps>00000000-0000-0000-0000-00005e4691b4</tstamps>
    </comp>
    <comp ref="D6">
      <value>bat46</value>
      <footprint>Diode_THT:D_DO-35_SOD27_P7.62mm_Horizontal</footprint>
      <libsource lib="Sync-Ope-proto-rescue" part="D_Schottky-Device" description=""/>
      <property name="Sheetname" value=""/>
      <property name="Sheetfile" value="sync_ope.kicad_sch"/>
      <sheetpath names="/" tstamps="/"/>
      <tstamps>d8dad053-14f1-4d56-b65a-24435adcf635</tstamps>
    </comp>
    <comp ref="D7">
      <value>1n4007</value>
      <footprint>Diode_THT:D_DO-35_SOD27_P10.16mm_Horizontal</footprint>
      <libsource lib="Sync-Ope-proto-rescue" part="D-Device" description=""/>
      <property name="Sheetname" value=""/>
      <property name="Sheetfile" value="sync_ope.kicad_sch"/>
      <sheetpath names="/" tstamps="/"/>
      <tstamps>00000000-0000-0000-0000-000062480531</tstamps>
    </comp>
    <comp ref="D8">
      <value>bat46</value>
      <footprint>Diode_THT:D_DO-35_SOD27_P7.62mm_Horizontal</footprint>
      <libsource lib="Sync-Ope-proto-rescue" part="D_Schottky-Device" description=""/>
      <property name="Sheetname" value=""/>
      <property name="Sheetfile" value="sync_ope.kicad_sch"/>
      <sheetpath names="/" tstamps="/"/>
      <tstamps>1a60b3e5-0606-48ed-baa6-b10ac667ea93</tstamps>
    </comp>
    <comp ref="J1">
      <value>rca</value>
      <footprint>lib_fp:tht_vertical_rca</footprint>
      <libsource lib="Sync-Ope-proto-rescue" part="Conn_Coaxial-Connector" description=""/>
      <property name="Sheetname" value=""/>
      <property name="Sheetfile" value="sync_ope.kicad_sch"/>
      <sheetpath names="/" tstamps="/"/>
      <tstamps>00000000-0000-0000-0000-00005e12d073</tstamps>
    </comp>
    <comp ref="J2">
      <value>barrel_jack</value>
      <footprint>lib_fp:BarrelJack_Horizontal</footprint>
      <libsource lib="Sync-Ope-proto-rescue" part="Barrel_Jack_Switch-Connector" description=""/>
      <property name="Sheetname" value=""/>
      <property name="Sheetfile" value="sync_ope.kicad_sch"/>
      <sheetpath names="/" tstamps="/"/>
      <tstamps>00000000-0000-0000-0000-00005e177836</tstamps>
    </comp>
    <comp ref="J3">
      <value>europower</value>
      <footprint>Connector_PinHeader_2.54mm:PinHeader_2x08_P2.54mm_Vertical</footprint>
      <libsource lib="Sync-Ope-proto-rescue" part="Conn_02x08_Odd_Even-Connector_Generic" description=""/>
      <property name="Sheetname" value=""/>
      <property name="Sheetfile" value="sync_ope.kicad_sch"/>
      <sheetpath names="/" tstamps="/"/>
      <tstamps>00000000-0000-0000-0000-00005de11e65</tstamps>
    </comp>
    <comp ref="J4">
      <value>mono_jack_3.5mm</value>
      <footprint>lib_fp:Jack_3.5mm_QingPu_WQP-PJ398SM_Vertical_CircularHoles</footprint>
      <libsource lib="Sync-Ope-proto-rescue" part="AudioJack2_SwitchT-Connector" description=""/>
      <property name="Sheetname" value=""/>
      <property name="Sheetfile" value="sync_ope.kicad_sch"/>
      <sheetpath names="/" tstamps="/"/>
      <tstamps>00000000-0000-0000-0000-00006011d58f</tstamps>
    </comp>
    <comp ref="J5">
      <value>mono_jack_3.5mm</value>
      <footprint>lib_fp:Jack_3.5mm_QingPu_WQP-PJ398SM_Vertical_CircularHoles</footprint>
      <libsource lib="Sync-Ope-proto-rescue" part="AudioJack2_SwitchT-Connector" description=""/>
      <property name="Sheetname" value=""/>
      <property name="Sheetfile" value="sync_ope.kicad_sch"/>
      <sheetpath names="/" tstamps="/"/>
      <tstamps>00000000-0000-0000-0000-00005e2ffc69</tstamps>
    </comp>
    <comp ref="J6">
      <value>rca</value>
      <footprint>lib_fp:tht_vertical_rca</footprint>
      <libsource lib="Sync-Ope-proto-rescue" part="Conn_Coaxial-Connector" description=""/>
      <property name="Sheetname" value=""/>
      <property name="Sheetfile" value="sync_ope.kicad_sch"/>
      <sheetpath names="/" tstamps="/"/>
      <tstamps>00000000-0000-0000-0000-00005ee5d0d4</tstamps>
    </comp>
    <comp ref="J7">
      <value>diy_power_header</value>
      <footprint>Connector_PinHeader_2.54mm:PinHeader_1x03_P2.54mm_Vertical</footprint>
      <libsource lib="Sync-Ope-proto-rescue" part="Conn_01x03_Female-Connector" description=""/>
      <property name="Sheetname" value=""/>
      <property name="Sheetfile" value="sync_ope.kicad_sch"/>
      <sheetpath names="/" tstamps="/"/>
      <tstamps>00000000-0000-0000-0000-00005e2c1545</tstamps>
    </comp>
    <comp ref="J8">
      <value>mono_jack_3.5mm</value>
      <footprint>lib_fp:Jack_3.5mm_QingPu_WQP-PJ398SM_Vertical_CircularHoles</footprint>
      <libsource lib="Sync-Ope-proto-rescue" part="AudioJack2_SwitchT-Connector" description=""/>
      <property name="Sheetname" value=""/>
      <property name="Sheetfile" value="sync_ope.kicad_sch"/>
      <sheetpath names="/" tstamps="/"/>
      <tstamps>00000000-0000-0000-0000-00005e2ceded</tstamps>
    </comp>
    <comp ref="J9">
      <value>rca</value>
      <footprint>lib_fp:tht_vertical_rca</footprint>
      <libsource lib="Sync-Ope-proto-rescue" part="Conn_Coaxial-Connector" description=""/>
      <property name="Sheetname" value=""/>
      <property name="Sheetfile" value="sync_ope.kicad_sch"/>
      <sheetpath names="/" tstamps="/"/>
      <tstamps>00000000-0000-0000-0000-00005ee6dfb3</tstamps>
    </comp>
    <comp ref="J10">
      <value>rca</value>
      <footprint>lib_fp:tht_vertical_rca</footprint>
      <libsource lib="Sync-Ope-proto-rescue" part="Conn_Coaxial-Connector" description=""/>
      <property name="Sheetname" value=""/>
      <property name="Sheetfile" value="sync_ope.kicad_sch"/>
      <sheetpath names="/" tstamps="/"/>
      <tstamps>00000000-0000-0000-0000-00005e165212</tstamps>
    </comp>
    <comp ref="L1">
      <value>100uH</value>
      <footprint>Inductor_THT:L_Radial_D10.0mm_P5.00mm_Neosid_SD12k_style3</footprint>
      <libsource lib="pspice" part="INDUCTOR" description="Inductor symbol for simulation only"/>
      <property name="Sheetname" value=""/>
      <property name="Sheetfile" value="sync_ope.kicad_sch"/>
      <property name="ki_description" value="Inductor symbol for simulation only"/>
      <property name="ki_keywords" value="simulation"/>
      <sheetpath names="/" tstamps="/"/>
      <tstamps>96bc1466-15ee-43e2-bb4e-1677b596e417</tstamps>
    </comp>
    <comp ref="L2">
      <value>100uH</value>
      <footprint>Inductor_THT:L_Radial_D10.0mm_P5.00mm_Neosid_SD12k_style3</footprint>
      <libsource lib="pspice" part="INDUCTOR" description="Inductor symbol for simulation only"/>
      <property name="Sheetname" value=""/>
      <property name="Sheetfile" value="sync_ope.kicad_sch"/>
      <property name="ki_description" value="Inductor symbol for simulation only"/>
      <property name="ki_keywords" value="simulation"/>
      <sheetpath names="/" tstamps="/"/>
      <tstamps>67880582-a53c-41bf-a69e-d4004f9df675</tstamps>
    </comp>
    <comp ref="R1">
      <value>75</value>
      <footprint>Resistor_THT:R_Axial_DIN0204_L3.6mm_D1.6mm_P7.62mm_Horizontal</footprint>
      <libsource lib="Sync-Ope-proto-rescue" part="R-Sync-Ope-proto-Sync-Ope-proto-rescue" description=""/>
      <property name="Sheetname" value=""/>
      <property name="Sheetfile" value="sync_ope.kicad_sch"/>
      <sheetpath names="/" tstamps="/"/>
      <tstamps>00000000-0000-0000-0000-00005db6bd67</tstamps>
    </comp>
    <comp ref="R2">
      <value>1.5k</value>
      <footprint>Resistor_THT:R_Axial_DIN0204_L3.6mm_D1.6mm_P7.62mm_Horizontal</footprint>
      <libsource lib="Sync-Ope-proto-rescue" part="R-Device" description=""/>
      <property name="Sheetname" value=""/>
      <property name="Sheetfile" value="sync_ope.kicad_sch"/>
      <sheetpath names="/" tstamps="/"/>
      <tstamps>00000000-0000-0000-0000-00005dc46a82</tstamps>
    </comp>
    <comp ref="R3">
      <value>510</value>
      <footprint>Resistor_THT:R_Axial_DIN0204_L3.6mm_D1.6mm_P7.62mm_Horizontal</footprint>
      <libsource lib="Sync-Ope-proto-rescue" part="R-Sync-Ope-proto-Sync-Ope-proto-rescue" description=""/>
      <property name="Sheetname" value=""/>
      <property name="Sheetfile" value="sync_ope.kicad_sch"/>
      <sheetpath names="/" tstamps="/"/>
      <tstamps>00000000-0000-0000-0000-000060371783</tstamps>
    </comp>
    <comp ref="R4">
      <value>1.5k</value>
      <footprint>Resistor_THT:R_Axial_DIN0204_L3.6mm_D1.6mm_P7.62mm_Horizontal</footprint>
      <libsource lib="Sync-Ope-proto-rescue" part="R-Sync-Ope-proto-Sync-Ope-proto-rescue" description=""/>
      <property name="Sheetname" value=""/>
      <property name="Sheetfile" value="sync_ope.kicad_sch"/>
      <sheetpath names="/" tstamps="/"/>
      <tstamps>00000000-0000-0000-0000-00005db6be5e</tstamps>
    </comp>
    <comp ref="R5">
      <value>1.5k</value>
      <footprint>Resistor_THT:R_Axial_DIN0204_L3.6mm_D1.6mm_P7.62mm_Horizontal</footprint>
      <libsource lib="Sync-Ope-proto-rescue" part="R-Sync-Ope-proto-Sync-Ope-proto-rescue" description=""/>
      <property name="Sheetname" value=""/>
      <property name="Sheetfile" value="sync_ope.kicad_sch"/>
      <sheetpath names="/" tstamps="/"/>
      <tstamps>00000000-0000-0000-0000-00005db6be2d</tstamps>
    </comp>
    <comp ref="R6">
      <value>100</value>
      <footprint>Resistor_THT:R_Axial_DIN0204_L3.6mm_D1.6mm_P7.62mm_Horizontal</footprint>
      <libsource lib="Sync-Ope-proto-rescue" part="R-Device" description=""/>
      <property name="Sheetname" value=""/>
      <property name="Sheetfile" value="sync_ope.kicad_sch"/>
      <sheetpath names="/" tstamps="/"/>
      <tstamps>00000000-0000-0000-0000-00005dc4fb90</tstamps>
    </comp>
    <comp ref="R8">
      <value>39k</value>
      <footprint>Resistor_THT:R_Axial_DIN0204_L3.6mm_D1.6mm_P7.62mm_Horizontal</footprint>
      <libsource lib="Sync-Ope-proto-rescue" part="R-Device" description=""/>
      <property name="Sheetname" value=""/>
      <property name="Sheetfile" value="sync_ope.kicad_sch"/>
      <sheetpath names="/" tstamps="/"/>
      <tstamps>00000000-0000-0000-0000-00006011d586</tstamps>
    </comp>
    <comp ref="R9">
      <value>75</value>
      <footprint>Resistor_THT:R_Axial_DIN0204_L3.6mm_D1.6mm_P7.62mm_Horizontal</footprint>
      <libsource lib="Sync-Ope-proto-rescue" part="R-Sync-Ope-proto-Sync-Ope-proto-rescue" description=""/>
      <property name="Sheetname" value=""/>
      <property name="Sheetfile" value="sync_ope.kicad_sch"/>
      <sheetpath names="/" tstamps="/"/>
      <tstamps>00000000-0000-0000-0000-00005db71e30</tstamps>
    </comp>
    <comp ref="R10">
      <value>470k</value>
      <footprint>Resistor_THT:R_Axial_DIN0204_L3.6mm_D1.6mm_P7.62mm_Horizontal</footprint>
      <libsource lib="Sync-Ope-proto-rescue" part="R-Sync-Ope-proto-Sync-Ope-proto-rescue" description=""/>
      <property name="Sheetname" value=""/>
      <property name="Sheetfile" value="sync_ope.kicad_sch"/>
      <sheetpath names="/" tstamps="/"/>
      <tstamps>00000000-0000-0000-0000-00005db7f722</tstamps>
    </comp>
    <comp ref="R11">
      <value>220</value>
      <footprint>Resistor_THT:R_Axial_DIN0204_L3.6mm_D1.6mm_P7.62mm_Horizontal</footprint>
      <libsource lib="Sync-Ope-proto-rescue" part="R-Sync-Ope-proto-Sync-Ope-proto-rescue" description=""/>
      <property name="Sheetname" value=""/>
      <property name="Sheetfile" value="sync_ope.kicad_sch"/>
      <sheetpath names="/" tstamps="/"/>
      <tstamps>00000000-0000-0000-0000-00005db80eb4</tstamps>
    </comp>
    <comp ref="R12">
      <value>1.5k</value>
      <footprint>Resistor_THT:R_Axial_DIN0204_L3.6mm_D1.6mm_P7.62mm_Horizontal</footprint>
      <libsource lib="Sync-Ope-proto-rescue" part="R-Sync-Ope-proto-Sync-Ope-proto-rescue" description=""/>
      <property name="Sheetname" value=""/>
      <property name="Sheetfile" value="sync_ope.kicad_sch"/>
      <sheetpath names="/" tstamps="/"/>
      <tstamps>00000000-0000-0000-0000-00005db72713</tstamps>
    </comp>
    <comp ref="R13">
      <value>1.5k</value>
      <footprint>Resistor_THT:R_Axial_DIN0204_L3.6mm_D1.6mm_P7.62mm_Horizontal</footprint>
      <libsource lib="Sync-Ope-proto-rescue" part="R-Sync-Ope-proto-Sync-Ope-proto-rescue" description=""/>
      <property name="Sheetname" value=""/>
      <property name="Sheetfile" value="sync_ope.kicad_sch"/>
      <sheetpath names="/" tstamps="/"/>
      <tstamps>00000000-0000-0000-0000-00005db72840</tstamps>
    </comp>
    <comp ref="R14">
      <value>10k</value>
      <footprint>Resistor_THT:R_Axial_DIN0204_L3.6mm_D1.6mm_P7.62mm_Horizontal</footprint>
      <libsource lib="Device" part="R" description="Resistor"/>
      <property name="Sheetname" value=""/>
      <property name="Sheetfile" value="sync_ope.kicad_sch"/>
      <property name="ki_description" value="Resistor"/>
      <property name="ki_keywords" value="R res resistor"/>
      <sheetpath names="/" tstamps="/"/>
      <tstamps>00000000-0000-0000-0000-00005db7312b</tstamps>
    </comp>
    <comp ref="R15">
      <value>47k</value>
      <footprint>Resistor_THT:R_Axial_DIN0204_L3.6mm_D1.6mm_P7.62mm_Horizontal</footprint>
      <libsource lib="Sync-Ope-proto-rescue" part="R-Sync-Ope-proto-Sync-Ope-proto-rescue" description=""/>
      <property name="Sheetname" value=""/>
      <property name="Sheetfile" value="sync_ope.kicad_sch"/>
      <sheetpath names="/" tstamps="/"/>
      <tstamps>00000000-0000-0000-0000-00005db73d34</tstamps>
    </comp>
    <comp ref="R16">
      <value>75</value>
      <footprint>Resistor_THT:R_Axial_DIN0204_L3.6mm_D1.6mm_P7.62mm_Horizontal</footprint>
      <libsource lib="Sync-Ope-proto-rescue" part="R-Sync-Ope-proto-Sync-Ope-proto-rescue" description=""/>
      <property name="Sheetname" value=""/>
      <property name="Sheetfile" value="sync_ope.kicad_sch"/>
      <sheetpath names="/" tstamps="/"/>
      <tstamps>00000000-0000-0000-0000-00005db75a90</tstamps>
    </comp>
    <comp ref="RV1">
      <value>10k_pot</value>
      <footprint>lib_fp:Potentiometer_Vertical_Large</footprint>
      <libsource lib="Sync-Ope-proto-rescue" part="POT-Sync-Ope-proto-Sync-Ope-proto-rescue" description=""/>
      <property name="Sheetname" value=""/>
      <property name="Sheetfile" value="sync_ope.kicad_sch"/>
      <sheetpath names="/" tstamps="/"/>
      <tstamps>00000000-0000-0000-0000-00005db76f3b</tstamps>
    </comp>
    <comp ref="U1">
      <value>AD8072</value>
      <footprint>lib_fp:DIP-SOIC-8</footprint>
      <libsource lib="Sync-Ope-proto-rescue" part="AD8072-Sync-Ope-proto-Sync-Ope-proto-rescue" description=""/>
      <property name="Sheetname" value=""/>
      <property name="Sheetfile" value="sync_ope.kicad_sch"/>
      <sheetpath names="/" tstamps="/"/>
      <tstamps>00000000-0000-0000-0000-00005db6bb03 00000000-0000-0000-0000-00005db6bab3</tstamps>
    </comp>
    <comp ref="U2">
      <value>LM2575-5.0BT</value>
      <footprint>Package_TO_SOT_THT:TO-220-5_Vertical</footprint>
      <datasheet>http://ww1.microchip.com/downloads/en/DeviceDoc/lm2575.pdf</datasheet>
      <libsource lib="Regulator_Switching" part="LM2575-5.0BT" description="Fixed 5.0V 52kHz Simple 1A Buck Regulator, TO-220-5"/>
      <property name="Sheetname" value=""/>
      <property name="Sheetfile" value="sync_ope.kicad_sch"/>
      <property name="ki_description" value="Fixed 5.0V 52kHz Simple 1A Buck Regulator, TO-220-5"/>
      <property name="ki_keywords" value="Buck regulator Switcher"/>
      <sheetpath names="/" tstamps="/"/>
      <tstamps>a5a635e3-1151-4208-868f-c1bd15c5da87</tstamps>
    </comp>
    <comp ref="U3">
      <value>LM2575-5.0BT</value>
      <footprint>Package_TO_SOT_THT:TO-220-5_Vertical</footprint>
      <datasheet>http://ww1.microchip.com/downloads/en/DeviceDoc/lm2575.pdf</datasheet>
      <libsource lib="Regulator_Switching" part="LM2575-5.0BT" description="Fixed 5.0V 52kHz Simple 1A Buck Regulator, TO-220-5"/>
      <property name="Sheetname" value=""/>
      <property name="Sheetfile" value="sync_ope.kicad_sch"/>
      <property name="ki_description" value="Fixed 5.0V 52kHz Simple 1A Buck Regulator, TO-220-5"/>
      <property name="ki_keywords" value="Buck regulator Switcher"/>
      <sheetpath names="/" tstamps="/"/>
      <tstamps>c94664de-8249-487f-991a-4a8ab762d9e3</tstamps>
    </comp>
    <comp ref="U4">
      <value>LT1251</value>
      <footprint>lib_fp:DIP+SOIC_14</footprint>
      <libsource lib="Sync-Ope-proto-rescue" part="LT1251-Sync-Ope-proto-Sync-Ope-proto-rescue" description=""/>
      <property name="Sheetname" value=""/>
      <property name="Sheetfile" value="sync_ope.kicad_sch"/>
      <sheetpath names="/" tstamps="/"/>
      <tstamps>00000000-0000-0000-0000-00005db717d4</tstamps>
    </comp>
    <comp ref="C17">
      <value>0.1u</value>
      <footprint>Capacitor_THT:C_Disc_D4.3mm_W1.9mm_P5.00mm</footprint>
      <libsource lib="Sync-Ope-proto-rescue" part="C-Sync-Ope-proto-Sync-Ope-proto-rescue" description=""/>
      <property name="Sheetname" value="blanking"/>
      <property name="Sheetfile" value="blanking.kicad_sch"/>
      <sheetpath names="/blanking/" tstamps="/00000000-0000-0000-0000-00005fdd6789/"/>
      <tstamps>00000000-0000-0000-0000-00005fdf1a8a</tstamps>
    </comp>
    <comp ref="C18">
      <value>0.1u</value>
      <footprint>Capacitor_THT:C_Disc_D4.3mm_W1.9mm_P5.00mm</footprint>
      <libsource lib="Sync-Ope-proto-rescue" part="C-Sync-Ope-proto-Sync-Ope-proto-rescue" description=""/>
      <property name="Sheetname" value="blanking"/>
      <property name="Sheetfile" value="blanking.kicad_sch"/>
      <sheetpath names="/blanking/" tstamps="/00000000-0000-0000-0000-00005fdd6789/"/>
      <tstamps>00000000-0000-0000-0000-00005fdf1aa6</tstamps>
    </comp>
    <comp ref="C19">
      <value>1nf_poly</value>
      <footprint>Capacitor_THT:C_Disc_D4.3mm_W1.9mm_P5.00mm</footprint>
      <libsource lib="Device" part="C_Small" description="Unpolarized capacitor, small symbol"/>
      <property name="Sheetname" value="blanking"/>
      <property name="Sheetfile" value="blanking.kicad_sch"/>
      <property name="ki_description" value="Unpolarized capacitor, small symbol"/>
      <property name="ki_keywords" value="capacitor cap"/>
      <sheetpath names="/blanking/" tstamps="/00000000-0000-0000-0000-00005fdd6789/"/>
      <tstamps>00000000-0000-0000-0000-000061573b82</tstamps>
    </comp>
    <comp ref="C20">
      <value>0.1u_poly</value>
      <footprint>Capacitor_THT:C_Disc_D4.3mm_W1.9mm_P5.00mm</footprint>
      <libsource lib="Device" part="C_Small" description="Unpolarized capacitor, small symbol"/>
      <property name="Sheetname" value="blanking"/>
      <property name="Sheetfile" value="blanking.kicad_sch"/>
      <property name="ki_description" value="Unpolarized capacitor, small symbol"/>
      <property name="ki_keywords" value="capacitor cap"/>
      <sheetpath names="/blanking/" tstamps="/00000000-0000-0000-0000-00005fdd6789/"/>
      <tstamps>00000000-0000-0000-0000-00005fddbcf9</tstamps>
    </comp>
    <comp ref="C21">
      <value>1nf_poly</value>
      <footprint>Capacitor_THT:C_Disc_D4.3mm_W1.9mm_P5.00mm</footprint>
      <libsource lib="Device" part="C_Small" description="Unpolarized capacitor, small symbol"/>
      <property name="Sheetname" value="blanking"/>
      <property name="Sheetfile" value="blanking.kicad_sch"/>
      <property name="ki_description" value="Unpolarized capacitor, small symbol"/>
      <property name="ki_keywords" value="capacitor cap"/>
      <sheetpath names="/blanking/" tstamps="/00000000-0000-0000-0000-00005fdd6789/"/>
      <tstamps>00000000-0000-0000-0000-000061573bd0</tstamps>
    </comp>
    <comp ref="C22">
      <value>1uf_poly</value>
      <footprint>Capacitor_THT:C_Disc_D4.3mm_W1.9mm_P5.00mm</footprint>
      <libsource lib="Device" part="C_Small" description="Unpolarized capacitor, small symbol"/>
      <property name="Sheetname" value="blanking"/>
      <property name="Sheetfile" value="blanking.kicad_sch"/>
      <property name="ki_description" value="Unpolarized capacitor, small symbol"/>
      <property name="ki_keywords" value="capacitor cap"/>
      <sheetpath names="/blanking/" tstamps="/00000000-0000-0000-0000-00005fdd6789/"/>
      <tstamps>00000000-0000-0000-0000-00006151f967</tstamps>
    </comp>
    <comp ref="D5">
      <value>LED</value>
      <footprint>LED_THT:LED_D3.0mm</footprint>
      <libsource lib="Sync-Ope-proto-rescue" part="LED-Device" description=""/>
      <property name="Sheetname" value="blanking"/>
      <property name="Sheetfile" value="blanking.kicad_sch"/>
      <sheetpath names="/blanking/" tstamps="/00000000-0000-0000-0000-00005fdd6789/"/>
      <tstamps>00000000-0000-0000-0000-00005fdf1acc</tstamps>
    </comp>
    <comp ref="J11">
      <value>Conn_01x02</value>
      <footprint>Connector_PinHeader_2.54mm:PinHeader_1x02_P2.54mm_Vertical</footprint>
      <libsource lib="Connector_Generic" part="Conn_01x02" description="Generic connector, single row, 01x02, script generated (kicad-library-utils/schlib/autogen/connector/)"/>
      <property name="Sheetname" value="blanking"/>
      <property name="Sheetfile" value="blanking.kicad_sch"/>
      <property name="ki_description" value="Generic connector, single row, 01x02, script generated (kicad-library-utils/schlib/autogen/connector/)"/>
      <property name="ki_keywords" value="connector"/>
      <sheetpath names="/blanking/" tstamps="/00000000-0000-0000-0000-00005fdd6789/"/>
      <tstamps>1cf0eb54-6c4b-414e-ac44-00a7598aa4a1</tstamps>
    </comp>
    <comp ref="R17">
      <value>680k</value>
      <footprint>Resistor_THT:R_Axial_DIN0204_L3.6mm_D1.6mm_P7.62mm_Horizontal</footprint>
      <libsource lib="Sync-Ope-proto-rescue" part="R-Sync-Ope-proto-Sync-Ope-proto-rescue" description=""/>
      <property name="Sheetname" value="blanking"/>
      <property name="Sheetfile" value="blanking.kicad_sch"/>
      <sheetpath names="/blanking/" tstamps="/00000000-0000-0000-0000-00005fdd6789/"/>
      <tstamps>00000000-0000-0000-0000-00005fdf1aa0</tstamps>
    </comp>
    <comp ref="R18">
      <value>1k</value>
      <footprint>Resistor_THT:R_Axial_DIN0204_L3.6mm_D1.6mm_P7.62mm_Horizontal</footprint>
      <libsource lib="Sync-Ope-proto-rescue" part="R-Sync-Ope-proto-Sync-Ope-proto-rescue" description=""/>
      <property name="Sheetname" value="blanking"/>
      <property name="Sheetfile" value="blanking.kicad_sch"/>
      <sheetpath names="/blanking/" tstamps="/00000000-0000-0000-0000-00005fdd6789/"/>
      <tstamps>00000000-0000-0000-0000-00005fdf1ac6</tstamps>
    </comp>
    <comp ref="R19">
      <value>10k</value>
      <footprint>Resistor_THT:R_Axial_DIN0204_L3.6mm_D1.6mm_P7.62mm_Horizontal</footprint>
      <libsource lib="Device" part="R" description="Resistor"/>
      <property name="Sheetname" value="blanking"/>
      <property name="Sheetfile" value="blanking.kicad_sch"/>
      <property name="ki_description" value="Resistor"/>
      <property name="ki_keywords" value="R res resistor"/>
      <sheetpath names="/blanking/" tstamps="/00000000-0000-0000-0000-00005fdd6789/"/>
      <tstamps>00000000-0000-0000-0000-000061573b8c</tstamps>
    </comp>
    <comp ref="R20">
      <value>15k</value>
      <footprint>Resistor_THT:R_Axial_DIN0204_L3.6mm_D1.6mm_P7.62mm_Horizontal</footprint>
      <libsource lib="Device" part="R" description="Resistor"/>
      <property name="Sheetname" value="blanking"/>
      <property name="Sheetfile" value="blanking.kicad_sch"/>
      <property name="ki_description" value="Resistor"/>
      <property name="ki_keywords" value="R res resistor"/>
      <sheetpath names="/blanking/" tstamps="/00000000-0000-0000-0000-00005fdd6789/"/>
      <tstamps>00000000-0000-0000-0000-00005fddbcff</tstamps>
    </comp>
    <comp ref="R21">
      <value>68k</value>
      <footprint>Resistor_THT:R_Axial_DIN0204_L3.6mm_D1.6mm_P7.62mm_Horizontal</footprint>
      <libsource lib="Device" part="R" description="Resistor"/>
      <property name="Sheetname" value="blanking"/>
      <property name="Sheetfile" value="blanking.kicad_sch"/>
      <property name="ki_description" value="Resistor"/>
      <property name="ki_keywords" value="R res resistor"/>
      <sheetpath names="/blanking/" tstamps="/00000000-0000-0000-0000-00005fdd6789/"/>
      <tstamps>00000000-0000-0000-0000-000061573bda</tstamps>
    </comp>
    <comp ref="R22">
      <value>12k</value>
      <footprint>Resistor_THT:R_Axial_DIN0204_L3.6mm_D1.6mm_P7.62mm_Horizontal</footprint>
      <libsource lib="Device" part="R" description="Resistor"/>
      <property name="Sheetname" value="blanking"/>
      <property name="Sheetfile" value="blanking.kicad_sch"/>
      <property name="ki_description" value="Resistor"/>
      <property name="ki_keywords" value="R res resistor"/>
      <sheetpath names="/blanking/" tstamps="/00000000-0000-0000-0000-00005fdd6789/"/>
      <tstamps>00000000-0000-0000-0000-00006151f971</tstamps>
    </comp>
    <comp ref="RV2">
      <value>5k_trim</value>
      <footprint>lib_fp:tht_vertical_trim_3362</footprint>
      <libsource lib="sync_ope-rescue" part="R_POT-Device" description=""/>
      <property name="Sheetname" value="blanking"/>
      <property name="Sheetfile" value="blanking.kicad_sch"/>
      <sheetpath names="/blanking/" tstamps="/00000000-0000-0000-0000-00005fdd6789/"/>
      <tstamps>00000000-0000-0000-0000-000061573b97</tstamps>
    </comp>
    <comp ref="RV3">
      <value>20k_trim</value>
      <footprint>lib_fp:tht_vertical_trim_3362</footprint>
      <libsource lib="sync_ope-rescue" part="R_POT-Device" description=""/>
      <property name="Sheetname" value="blanking"/>
      <property name="Sheetfile" value="blanking.kicad_sch"/>
      <sheetpath names="/blanking/" tstamps="/00000000-0000-0000-0000-00005fdd6789/"/>
      <tstamps>00000000-0000-0000-0000-00005fddbd07</tstamps>
    </comp>
    <comp ref="RV4">
      <value>10k_trim</value>
      <footprint>lib_fp:tht_vertical_trim_3362</footprint>
      <libsource lib="sync_ope-rescue" part="R_POT-Device" description=""/>
      <property name="Sheetname" value="blanking"/>
      <property name="Sheetfile" value="blanking.kicad_sch"/>
      <sheetpath names="/blanking/" tstamps="/00000000-0000-0000-0000-00005fdd6789/"/>
      <tstamps>00000000-0000-0000-0000-000061573be5</tstamps>
    </comp>
    <comp ref="RV5">
      <value>20k_trim</value>
      <footprint>lib_fp:tht_vertical_trim_3362</footprint>
      <libsource lib="sync_ope-rescue" part="R_POT-Device" description=""/>
      <property name="Sheetname" value="blanking"/>
      <property name="Sheetfile" value="blanking.kicad_sch"/>
      <sheetpath names="/blanking/" tstamps="/00000000-0000-0000-0000-00005fdd6789/"/>
      <tstamps>00000000-0000-0000-0000-00006151f97c</tstamps>
    </comp>
    <comp ref="U5">
      <value>74HC4538</value>
      <footprint>Package_DIP:DIP-16_W7.62mm_LongPads</footprint>
      <datasheet>https://assets.nexperia.com/documents/data-sheet/HEF4538B.pdf</datasheet>
      <libsource lib="74hc4538" part="74HC4538" description=""/>
      <property name="Sheetname" value="blanking"/>
      <property name="Sheetfile" value="blanking.kicad_sch"/>
      <sheetpath names="/blanking/" tstamps="/00000000-0000-0000-0000-00005fdd6789/"/>
      <tstamps>00000000-0000-0000-0000-000061573896 00000000-0000-0000-0000-000061573baf 00000000-0000-0000-0000-00005fddbd1c</tstamps>
    </comp>
    <comp ref="U6">
      <value>74HC4538</value>
      <footprint>Package_DIP:DIP-16_W7.62mm_LongPads</footprint>
      <datasheet>https://assets.nexperia.com/documents/data-sheet/HEF4538B.pdf</datasheet>
      <libsource lib="74hc4538" part="74HC4538" description=""/>
      <property name="Sheetname" value="blanking"/>
      <property name="Sheetfile" value="blanking.kicad_sch"/>
      <sheetpath names="/blanking/" tstamps="/00000000-0000-0000-0000-00005fdd6789/"/>
      <tstamps>00000000-0000-0000-0000-00006151f7c0 00000000-0000-0000-0000-00006150d696 00000000-0000-0000-0000-00005fddbce1</tstamps>
    </comp>
    <comp ref="U7">
      <value>LM1881</value>
      <footprint>lib_fp:DIP-SOIC-8</footprint>
      <libsource lib="Video" part="LM1881" description=""/>
      <property name="Sheetname" value="blanking"/>
      <property name="Sheetfile" value="blanking.kicad_sch"/>
      <sheetpath names="/blanking/" tstamps="/00000000-0000-0000-0000-00005fdd6789/"/>
      <tstamps>00000000-0000-0000-0000-00006038e4ba</tstamps>
    </comp>
    <comp ref="U8">
      <value>74HC4053</value>
      <footprint>Package_DIP:DIP-16_W7.62mm_LongPads</footprint>
      <datasheet>http://www.ti.com/lit/ds/symlink/cd4052b.pdf</datasheet>
      <libsource lib="Sync-Ope-proto-rescue" part="CD4053B-Analog_Switch" description=""/>
      <property name="Sheetname" value="blanking"/>
      <property name="Sheetfile" value="blanking.kicad_sch"/>
      <sheetpath names="/blanking/" tstamps="/00000000-0000-0000-0000-00005fdd6789/"/>
      <tstamps>00000000-0000-0000-0000-00005fddbcd5</tstamps>
    </comp>
  </components>
  <libparts>
    <libpart lib="74hc4538" part="74HC4538">
      <footprints>
        <fp>DIP?16*</fp>
      </footprints>
      <fields>
        <field name="Reference">U</field>
        <field name="Value">74HC4538</field>
      </fields>
      <pins>
        <pin num="1" name="Cx" type="input"/>
        <pin num="2" name="RxCx" type="input"/>
        <pin num="3" name="~{CD}" type="input"/>
        <pin num="4" name="B" type="input"/>
        <pin num="5" name="~{A}" type="input"/>
        <pin num="6" name="Q" type="output"/>
        <pin num="7" name="~{Q}" type="output"/>
        <pin num="8" name="VSS" type="power_in"/>
        <pin num="9" name="~{Q}" type="output"/>
        <pin num="10" name="Q" type="output"/>
        <pin num="11" name="~{A}" type="input"/>
        <pin num="12" name="B" type="input"/>
        <pin num="13" name="~{CD}" type="input"/>
        <pin num="14" name="RxCx" type="input"/>
        <pin num="15" name="Cx" type="input"/>
        <pin num="16" name="VDD" type="power_in"/>
      </pins>
    </libpart>
    <libpart lib="Connector_Generic" part="Conn_01x02">
      <description>Generic connector, single row, 01x02, script generated (kicad-library-utils/schlib/autogen/connector/)</description>
      <docs>~</docs>
      <footprints>
        <fp>Connector*:*_1x??_*</fp>
      </footprints>
      <fields>
        <field name="Reference">J</field>
        <field name="Value">Conn_01x02</field>
        <field name="Datasheet">~</field>
      </fields>
      <pins>
        <pin num="1" name="Pin_1" type="passive"/>
        <pin num="2" name="Pin_2" type="passive"/>
      </pins>
    </libpart>
    <libpart lib="Device" part="C_Polarized">
      <description>Polarized capacitor</description>
      <docs>~</docs>
      <footprints>
        <fp>CP_*</fp>
      </footprints>
      <fields>
        <field name="Reference">C</field>
        <field name="Value">C_Polarized</field>
        <field name="Datasheet">~</field>
      </fields>
      <pins>
        <pin num="1" name="" type="passive"/>
        <pin num="2" name="" type="passive"/>
      </pins>
    </libpart>
    <libpart lib="Device" part="C_Small">
      <description>Unpolarized capacitor, small symbol</description>
      <docs>~</docs>
      <footprints>
        <fp>C_*</fp>
      </footprints>
      <fields>
        <field name="Reference">C</field>
        <field name="Value">C_Small</field>
        <field name="Datasheet">~</field>
      </fields>
      <pins>
        <pin num="1" name="" type="passive"/>
        <pin num="2" name="" type="passive"/>
      </pins>
    </libpart>
    <libpart lib="Device" part="D_Schottky">
      <description>Schottky diode</description>
      <docs>~</docs>
      <footprints>
        <fp>TO-???*</fp>
        <fp>*_Diode_*</fp>
        <fp>*SingleDiode*</fp>
        <fp>D_*</fp>
      </footprints>
      <fields>
        <field name="Reference">D</field>
        <field name="Value">D_Schottky</field>
        <field name="Datasheet">~</field>
      </fields>
      <pins>
        <pin num="1" name="K" type="passive"/>
        <pin num="2" name="A" type="passive"/>
      </pins>
    </libpart>
    <libpart lib="Device" part="R">
      <description>Resistor</description>
      <docs>~</docs>
      <footprints>
        <fp>R_*</fp>
      </footprints>
      <fields>
        <field name="Reference">R</field>
        <field name="Value">R</field>
        <field name="Datasheet">~</field>
      </fields>
      <pins>
        <pin num="1" name="" type="passive"/>
        <pin num="2" name="" type="passive"/>
      </pins>
    </libpart>
    <libpart lib="Regulator_Switching" part="LM2575-5.0BT">
      <description>Fixed 5.0V 52kHz Simple 1A Buck Regulator, TO-220-5</description>
      <docs>http://ww1.microchip.com/downloads/en/DeviceDoc/lm2575.pdf</docs>
      <footprints>
        <fp>TO?220*</fp>
      </footprints>
      <fields>
        <field name="Reference">U</field>
        <field name="Value">LM2575-5.0BT</field>
        <field name="Footprint">Package_TO_SOT_THT:TO-220-5_Vertical</field>
        <field name="Datasheet">http://ww1.microchip.com/downloads/en/DeviceDoc/lm2575.pdf</field>
      </fields>
      <pins>
        <pin num="1" name="VIN" type="power_in"/>
        <pin num="2" name="OUT" type="output"/>
        <pin num="3" name="GND" type="power_in"/>
        <pin num="4" name="FB" type="input"/>
        <pin num="5" name="~{ON}/OFF" type="input"/>
      </pins>
    </libpart>
    <libpart lib="Sync-Ope-proto-rescue" part="AD8072-Sync-Ope-proto-Sync-Ope-proto-rescue">
      <footprints>
        <fp>SOIC*3.9x4.9mm*Pitch1.27mm*</fp>
        <fp>DIP*W7.62mm*</fp>
        <fp>TO*99*</fp>
        <fp>OnSemi*Micro8*</fp>
        <fp>TSSOP*3x3mm*Pitch0.65mm*</fp>
        <fp>TSSOP*4.4x3mm*Pitch0.65mm*</fp>
        <fp>MSOP*3x3mm*Pitch0.65mm*</fp>
        <fp>SSOP*3.9x4.9mm*Pitch0.635mm*</fp>
        <fp>LFCSP*2x2mm*Pitch0.5mm*</fp>
        <fp>*SIP*</fp>
        <fp>SOIC*5.3x6.2mm*Pitch1.27mm*</fp>
      </footprints>
      <fields>
        <field name="Reference">U</field>
        <field name="Value">AD8072-Sync-Ope-proto-Sync-Ope-proto-rescue</field>
      </fields>
      <pins>
        <pin num="1" name="" type="output"/>
        <pin num="2" name="-" type="input"/>
        <pin num="3" name="+" type="input"/>
        <pin num="4" name="V-" type="power_in"/>
        <pin num="5" name="+" type="input"/>
        <pin num="6" name="-" type="input"/>
        <pin num="7" name="" type="output"/>
        <pin num="8" name="V+" type="power_in"/>
      </pins>
    </libpart>
    <libpart lib="Sync-Ope-proto-rescue" part="AudioJack2_SwitchT-Connector">
      <footprints>
        <fp>Jack*</fp>
      </footprints>
      <fields>
        <field name="Reference">J</field>
        <field name="Value">AudioJack2_SwitchT-Connector</field>
      </fields>
      <pins>
        <pin num="S" name="" type="passive"/>
        <pin num="T" name="" type="passive"/>
        <pin num="TN" name="" type="passive"/>
      </pins>
    </libpart>
    <libpart lib="Sync-Ope-proto-rescue" part="Barrel_Jack_Switch-Connector">
      <footprints>
        <fp>BarrelJack*</fp>
      </footprints>
      <fields>
        <field name="Reference">J</field>
        <field name="Value">Barrel_Jack_Switch-Connector</field>
      </fields>
      <pins>
        <pin num="1" name="" type="passive"/>
        <pin num="2" name="" type="passive"/>
        <pin num="3" name="" type="passive"/>
      </pins>
    </libpart>
    <libpart lib="Sync-Ope-proto-rescue" part="C-Device">
      <footprints>
        <fp>C_*</fp>
      </footprints>
      <fields>
        <field name="Reference">C</field>
        <field name="Value">C-Device</field>
      </fields>
      <pins>
        <pin num="1" name="" type="passive"/>
        <pin num="2" name="" type="passive"/>
      </pins>
    </libpart>
    <libpart lib="Sync-Ope-proto-rescue" part="C-Sync-Ope-proto-Sync-Ope-proto-rescue">
      <footprints>
        <fp>C_*</fp>
      </footprints>
      <fields>
        <field name="Reference">C</field>
        <field name="Value">C-Sync-Ope-proto-Sync-Ope-proto-rescue</field>
      </fields>
      <pins>
        <pin num="1" name="" type="passive"/>
        <pin num="2" name="" type="passive"/>
      </pins>
    </libpart>
    <libpart lib="Sync-Ope-proto-rescue" part="CD4053B-Analog_Switch">
      <footprints>
        <fp>TSSOP*4.4x5mm*P0.65mm*</fp>
        <fp>DIP*W7.62*</fp>
        <fp>SOIC*3.9x9.9mm*P1.27mm*</fp>
        <fp>SO*5.3x10.2mm*P1.27mm*</fp>
      </footprints>
      <fields>
        <field name="Reference">U</field>
        <field name="Value">CD4053B-Analog_Switch</field>
      </fields>
      <pins>
        <pin num="1" name="Y1" type="bidirectional"/>
        <pin num="2" name="Y0" type="bidirectional"/>
        <pin num="3" name="Z1" type="bidirectional"/>
        <pin num="4" name="Z" type="bidirectional"/>
        <pin num="5" name="Z0" type="bidirectional"/>
        <pin num="6" name="INH" type="input"/>
        <pin num="7" name="VEE" type="power_in"/>
        <pin num="8" name="VSS" type="power_in"/>
        <pin num="9" name="C" type="input"/>
        <pin num="10" name="B" type="input"/>
        <pin num="11" name="A" type="input"/>
        <pin num="12" name="X0" type="bidirectional"/>
        <pin num="13" name="X1" type="bidirectional"/>
        <pin num="14" name="Y" type="bidirectional"/>
        <pin num="15" name="X" type="bidirectional"/>
        <pin num="16" name="VDD" type="power_in"/>
      </pins>
    </libpart>
    <libpart lib="Sync-Ope-proto-rescue" part="CP_Small-Device">
      <footprints>
        <fp>CP_*</fp>
      </footprints>
      <fields>
        <field name="Reference">C</field>
        <field name="Value">CP_Small-Device</field>
      </fields>
      <pins>
        <pin num="1" name="" type="passive"/>
        <pin num="2" name="" type="passive"/>
      </pins>
    </libpart>
    <libpart lib="Sync-Ope-proto-rescue" part="Conn_01x03_Female-Connector">
      <footprints>
        <fp>Connector*:*_1x??_*</fp>
      </footprints>
      <fields>
        <field name="Reference">J</field>
        <field name="Value">Conn_01x03_Female-Connector</field>
      </fields>
      <pins>
        <pin num="1" name="Pin_1" type="passive"/>
        <pin num="2" name="Pin_2" type="passive"/>
        <pin num="3" name="Pin_3" type="passive"/>
      </pins>
    </libpart>
    <libpart lib="Sync-Ope-proto-rescue" part="Conn_02x08_Odd_Even-Connector_Generic">
      <footprints>
        <fp>Connector*:*_2x??_*</fp>
      </footprints>
      <fields>
        <field name="Reference">J</field>
        <field name="Value">Conn_02x08_Odd_Even-Connector_Generic</field>
      </fields>
      <pins>
        <pin num="1" name="Pin_1" type="passive"/>
        <pin num="2" name="Pin_2" type="passive"/>
        <pin num="3" name="Pin_3" type="passive"/>
        <pin num="4" name="Pin_4" type="passive"/>
        <pin num="5" name="Pin_5" type="passive"/>
        <pin num="6" name="Pin_6" type="passive"/>
        <pin num="7" name="Pin_7" type="passive"/>
        <pin num="8" name="Pin_8" type="passive"/>
        <pin num="9" name="Pin_9" type="passive"/>
        <pin num="10" name="Pin_10" type="passive"/>
        <pin num="11" name="Pin_11" type="passive"/>
        <pin num="12" name="Pin_12" type="passive"/>
        <pin num="13" name="Pin_13" type="passive"/>
        <pin num="14" name="Pin_14" type="passive"/>
        <pin num="15" name="Pin_15" type="passive"/>
        <pin num="16" name="Pin_16" type="passive"/>
      </pins>
    </libpart>
    <libpart lib="Sync-Ope-proto-rescue" part="Conn_Coaxial-Connector">
      <footprints>
        <fp>*BNC*</fp>
        <fp>*SMA*</fp>
        <fp>*SMB*</fp>
        <fp>*SMC*</fp>
        <fp>*Cinch*</fp>
      </footprints>
      <fields>
        <field name="Reference">J</field>
        <field name="Value">Conn_Coaxial-Connector</field>
      </fields>
      <pins>
        <pin num="1" name="In" type="passive"/>
        <pin num="2" name="Ext" type="passive"/>
      </pins>
    </libpart>
    <libpart lib="Sync-Ope-proto-rescue" part="D-Device">
      <footprints>
        <fp>TO-???*</fp>
        <fp>*_Diode_*</fp>
        <fp>*SingleDiode*</fp>
        <fp>D_*</fp>
      </footprints>
      <fields>
        <field name="Reference">D</field>
        <field name="Value">D-Device</field>
      </fields>
      <pins>
        <pin num="1" name="K" type="passive"/>
        <pin num="2" name="A" type="passive"/>
      </pins>
    </libpart>
    <libpart lib="Sync-Ope-proto-rescue" part="D_Schottky-Device">
      <footprints>
        <fp>TO-???*</fp>
        <fp>*_Diode_*</fp>
        <fp>*SingleDiode*</fp>
        <fp>D_*</fp>
      </footprints>
      <fields>
        <field name="Reference">D</field>
        <field name="Value">D_Schottky-Device</field>
      </fields>
      <pins>
        <pin num="1" name="K" type="passive"/>
        <pin num="2" name="A" type="passive"/>
      </pins>
    </libpart>
    <libpart lib="Sync-Ope-proto-rescue" part="D_Zener-Device">
      <footprints>
        <fp>TO-???*</fp>
        <fp>*_Diode_*</fp>
        <fp>*SingleDiode*</fp>
        <fp>D_*</fp>
      </footprints>
      <fields>
        <field name="Reference">D</field>
        <field name="Value">D_Zener-Device</field>
      </fields>
      <pins>
        <pin num="1" name="K" type="passive"/>
        <pin num="2" name="A" type="passive"/>
      </pins>
    </libpart>
    <libpart lib="Sync-Ope-proto-rescue" part="LED-Device">
      <footprints>
        <fp>LED*</fp>
        <fp>LED_SMD:*</fp>
        <fp>LED_THT:*</fp>
      </footprints>
      <fields>
        <field name="Reference">D</field>
        <field name="Value">LED-Device</field>
      </fields>
      <pins>
        <pin num="1" name="K" type="passive"/>
        <pin num="2" name="A" type="passive"/>
      </pins>
    </libpart>
    <libpart lib="Sync-Ope-proto-rescue" part="LT1251-Sync-Ope-proto-Sync-Ope-proto-rescue">
      <fields>
        <field name="Reference">U</field>
        <field name="Value">LT1251-Sync-Ope-proto-Sync-Ope-proto-rescue</field>
      </fields>
      <pins>
        <pin num="1" name="IN_1" type="input"/>
        <pin num="2" name="FB_1" type="input"/>
        <pin num="3" name="V_CONTROL" type="input"/>
        <pin num="4" name="I_c" type="input"/>
        <pin num="5" name="R_c" type="input"/>
        <pin num="6" name="NULL" type="input"/>
        <pin num="7" name="V-" type="input"/>
        <pin num="8" name="V_OUT" type="output"/>
        <pin num="9" name="V+" type="input"/>
        <pin num="10" name="R_fs" type="input"/>
        <pin num="11" name="I_fs" type="power_in"/>
        <pin num="12" name="V_FS" type="input"/>
        <pin num="13" name="FB_2" type="output"/>
        <pin num="14" name="IN_2" type="output"/>
      </pins>
    </libpart>
    <libpart lib="Sync-Ope-proto-rescue" part="POT-Sync-Ope-proto-Sync-Ope-proto-rescue">
      <footprints>
        <fp>Potentiometer*</fp>
      </footprints>
      <fields>
        <field name="Reference">RV</field>
        <field name="Value">POT-Sync-Ope-proto-Sync-Ope-proto-rescue</field>
      </fields>
      <pins>
        <pin num="1" name="1" type="passive"/>
        <pin num="2" name="2" type="passive"/>
        <pin num="3" name="3" type="passive"/>
      </pins>
    </libpart>
    <libpart lib="Sync-Ope-proto-rescue" part="R-Device">
      <footprints>
        <fp>R_*</fp>
      </footprints>
      <fields>
        <field name="Reference">R</field>
        <field name="Value">R-Device</field>
      </fields>
      <pins>
        <pin num="1" name="" type="passive"/>
        <pin num="2" name="" type="passive"/>
      </pins>
    </libpart>
    <libpart lib="Sync-Ope-proto-rescue" part="R-Sync-Ope-proto-Sync-Ope-proto-rescue">
      <footprints>
        <fp>R_*</fp>
        <fp>R_*</fp>
      </footprints>
      <fields>
        <field name="Reference">R</field>
        <field name="Value">R-Sync-Ope-proto-Sync-Ope-proto-rescue</field>
      </fields>
      <pins>
        <pin num="1" name="" type="passive"/>
        <pin num="2" name="" type="passive"/>
      </pins>
    </libpart>
    <libpart lib="Video" part="LM1881">
      <fields>
        <field name="Reference">U</field>
        <field name="Value">LM1881</field>
      </fields>
      <pins>
        <pin num="1" name="CSYNC" type="output"/>
        <pin num="2" name="VIDEO" type="input"/>
        <pin num="3" name="FRAME" type="output"/>
        <pin num="4" name="GND" type="power_in"/>
        <pin num="5" name="BURST" type="output"/>
        <pin num="6" name="INT" type="input"/>
        <pin num="7" name="O/E" type="output"/>
        <pin num="8" name="VCC" type="power_in"/>
      </pins>
    </libpart>
    <libpart lib="pspice" part="INDUCTOR">
      <description>Inductor symbol for simulation only</description>
      <docs>~</docs>
      <fields>
        <field name="Reference">L</field>
        <field name="Value">INDUCTOR</field>
        <field name="Datasheet">~</field>
      </fields>
      <pins>
        <pin num="1" name="1" type="input"/>
        <pin num="2" name="2" type="input"/>
      </pins>
    </libpart>
    <libpart lib="sync_ope-rescue" part="R_POT-Device">
      <footprints>
        <fp>Potentiometer*</fp>
      </footprints>
      <fields>
        <field name="Reference">RV</field>
        <field name="Value">R_POT-Device</field>
      </fields>
      <pins>
        <pin num="1" name="1" type="passive"/>
        <pin num="2" name="2" type="passive"/>
        <pin num="3" name="3" type="passive"/>
      </pins>
    </libpart>
  </libparts>
  <libraries>
    <library logical="74hc4538">
      <uri>/home/timcaldwell/projects/sync_ope/hardware/lib_sch/74hc4538.lib</uri>
    </library>
    <library logical="Connector_Generic">
      <uri>/app/extensions/Library/symbols//Connector_Generic.kicad_sym</uri>
    </library>
    <library logical="Device">
      <uri>/app/extensions/Library/symbols//Device.kicad_sym</uri>
    </library>
    <library logical="Regulator_Switching">
      <uri>/app/extensions/Library/symbols//Regulator_Switching.kicad_sym</uri>
    </library>
    <library logical="Sync-Ope-proto-rescue">
      <uri>/home/timcaldwell/projects/sync_ope/hardware/Sync-Ope-proto-rescue.lib</uri>
    </library>
    <library logical="Video">
      <uri>/app/extensions/Library/symbols//Video.kicad_sym</uri>
    </library>
    <library logical="sync_ope-rescue">
      <uri>/home/timcaldwell/projects/sync_ope/hardware/sync_ope-rescue.lib</uri>
    </library>
  </libraries>
  <nets>
    <net code="1" name="+5V">
      <node ref="C10" pin="1" pintype="passive"/>
      <node ref="C12" pin="1" pintype="passive"/>
      <node ref="C14" pin="1" pintype="passive"/>
      <node ref="C15" pin="1" pintype="passive"/>
      <node ref="C23" pin="1" pintype="passive"/>
      <node ref="C3" pin="1" pintype="passive"/>
      <node ref="D6" pin="1" pinfunction="K" pintype="passive"/>
      <node ref="J7" pin="3" pinfunction="Pin_3" pintype="passive"/>
      <node ref="L2" pin="2" pinfunction="2" pintype="input"/>
      <node ref="R15" pin="1" pintype="passive"/>
      <node ref="R8" pin="1" pintype="passive"/>
      <node ref="RV2" pin="1" pinfunction="1" pintype="passive"/>
      <node ref="RV3" pin="1" pinfunction="1" pintype="passive"/>
      <node ref="RV4" pin="1" pinfunction="1" pintype="passive"/>
      <node ref="RV5" pin="1" pinfunction="1" pintype="passive"/>
      <node ref="U1" pin="8" pinfunction="V+" pintype="power_in"/>
      <node ref="U3" pin="4" pinfunction="FB" pintype="input"/>
      <node ref="U4" pin="9" pinfunction="V+" pintype="input"/>
      <node ref="U5" pin="13" pinfunction="~{CD}" pintype="input"/>
      <node ref="U5" pin="16" pinfunction="VDD" pintype="power_in"/>
      <node ref="U6" pin="13" pinfunction="~{CD}" pintype="input"/>
      <node ref="U6" pin="16" pinfunction="VDD" pintype="power_in"/>
      <node ref="U6" pin="3" pinfunction="~{CD}" pintype="input"/>
      <node ref="U7" pin="8" pinfunction="VCC" pintype="power_in"/>
      <node ref="U8" pin="16" pinfunction="VDD" pintype="power_in"/>
    </net>
    <net code="2" name="+12V">
      <node ref="C1" pin="1" pintype="passive"/>
      <node ref="D7" pin="1" pinfunction="K" pintype="passive"/>
      <node ref="U2" pin="1" pinfunction="VIN" pintype="power_in"/>
      <node ref="U3" pin="1" pinfunction="VIN" pintype="power_in"/>
    </net>
    <net code="3" name="-5V">
      <node ref="C11" pin="2" pintype="passive"/>
      <node ref="C13" pin="2" pintype="passive"/>
      <node ref="C2" pin="2" pintype="passive"/>
      <node ref="C25" pin="2" pintype="passive"/>
      <node ref="D1" pin="2" pinfunction="A" pintype="passive"/>
      <node ref="J7" pin="1" pinfunction="Pin_1" pintype="passive"/>
      <node ref="U1" pin="4" pinfunction="V-" pintype="power_in"/>
      <node ref="U2" pin="3" pinfunction="GND" pintype="power_in"/>
      <node ref="U2" pin="5" pinfunction="~{ON}/OFF" pintype="input"/>
      <node ref="U4" pin="7" pinfunction="V-" pintype="input"/>
      <node ref="U8" pin="7" pinfunction="VEE" pintype="power_in"/>
    </net>
    <net code="4" name="/blanking/control_blank">
      <node ref="D6" pin="2" pinfunction="A" pintype="passive"/>
      <node ref="D8" pin="1" pinfunction="K" pintype="passive"/>
      <node ref="J4" pin="T" pintype="passive"/>
      <node ref="U8" pin="3" pinfunction="Z1" pintype="bidirectional"/>
    </net>
    <net code="5" name="/blanking/control_pulse">
      <node ref="RV1" pin="1" pinfunction="1" pintype="passive"/>
      <node ref="U8" pin="4" pinfunction="Z" pintype="bidirectional"/>
    </net>
    <net code="6" name="/blanking/input_blank">
      <node ref="C4" pin="1" pintype="passive"/>
      <node ref="U1" pin="5" pinfunction="+" pintype="input"/>
      <node ref="U4" pin="14" pinfunction="IN_2" pintype="output"/>
      <node ref="U8" pin="14" pinfunction="Y" pintype="bidirectional"/>
    </net>
    <net code="7" name="/blanking/return_blank">
      <node ref="C24" pin="2" pintype="passive"/>
      <node ref="R9" pin="2" pintype="passive"/>
      <node ref="U8" pin="15" pinfunction="X" pintype="bidirectional"/>
    </net>
    <net code="8" name="/blanking/video_in">
      <node ref="C17" pin="2" pintype="passive"/>
      <node ref="J1" pin="1" pinfunction="In" pintype="passive"/>
      <node ref="R1" pin="1" pintype="passive"/>
      <node ref="R3" pin="2" pintype="passive"/>
    </net>
    <net code="9" name="GND">
      <node ref="C1" pin="2" pintype="passive"/>
      <node ref="C10" pin="2" pintype="passive"/>
      <node ref="C11" pin="1" pintype="passive"/>
      <node ref="C12" pin="2" pintype="passive"/>
      <node ref="C13" pin="1" pintype="passive"/>
      <node ref="C14" pin="2" pintype="passive"/>
      <node ref="C15" pin="2" pintype="passive"/>
      <node ref="C16" pin="2" pintype="passive"/>
      <node ref="C18" pin="2" pintype="passive"/>
      <node ref="C2" pin="1" pintype="passive"/>
      <node ref="C23" pin="2" pintype="passive"/>
      <node ref="C25" pin="1" pintype="passive"/>
      <node ref="C3" pin="2" pintype="passive"/>
      <node ref="D2" pin="2" pinfunction="A" pintype="passive"/>
      <node ref="D3" pin="2" pinfunction="A" pintype="passive"/>
      <node ref="D8" pin="2" pinfunction="A" pintype="passive"/>
      <node ref="J1" pin="2" pinfunction="Ext" pintype="passive"/>
      <node ref="J10" pin="2" pinfunction="Ext" pintype="passive"/>
      <node ref="J2" pin="2" pintype="passive"/>
      <node ref="J3" pin="3" pinfunction="Pin_3" pintype="passive"/>
      <node ref="J3" pin="4" pinfunction="Pin_4" pintype="passive"/>
      <node ref="J3" pin="5" pinfunction="Pin_5" pintype="passive"/>
      <node ref="J3" pin="6" pinfunction="Pin_6" pintype="passive"/>
      <node ref="J3" pin="7" pinfunction="Pin_7" pintype="passive"/>
      <node ref="J3" pin="8" pinfunction="Pin_8" pintype="passive"/>
      <node ref="J4" pin="S" pintype="passive"/>
      <node ref="J5" pin="S" pintype="passive"/>
      <node ref="J6" pin="2" pinfunction="Ext" pintype="passive"/>
      <node ref="J7" pin="2" pinfunction="Pin_2" pintype="passive"/>
      <node ref="J8" pin="S" pintype="passive"/>
      <node ref="J9" pin="2" pinfunction="Ext" pintype="passive"/>
      <node ref="L1" pin="2" pinfunction="2" pintype="input"/>
      <node ref="R1" pin="2" pintype="passive"/>
      <node ref="R10" pin="1" pintype="passive"/>
      <node ref="R14" pin="1" pintype="passive"/>
      <node ref="R17" pin="2" pintype="passive"/>
      <node ref="R18" pin="2" pintype="passive"/>
      <node ref="R2" pin="2" pintype="passive"/>
      <node ref="RV1" pin="3" pinfunction="3" pintype="passive"/>
      <node ref="U2" pin="4" pinfunction="FB" pintype="input"/>
      <node ref="U3" pin="3" pinfunction="GND" pintype="power_in"/>
      <node ref="U3" pin="5" pinfunction="~{ON}/OFF" pintype="input"/>
      <node ref="U4" pin="10" pinfunction="R_fs" pintype="input"/>
      <node ref="U4" pin="5" pinfunction="R_c" pintype="input"/>
      <node ref="U5" pin="12" pinfunction="B" pintype="input"/>
      <node ref="U5" pin="4" pinfunction="B" pintype="input"/>
      <node ref="U5" pin="8" pinfunction="VSS" pintype="power_in"/>
      <node ref="U6" pin="12" pinfunction="B" pintype="input"/>
      <node ref="U6" pin="4" pinfunction="B" pintype="input"/>
      <node ref="U6" pin="8" pinfunction="VSS" pintype="power_in"/>
      <node ref="U7" pin="4" pinfunction="GND" pintype="power_in"/>
      <node ref="U8" pin="12" pinfunction="X0" pintype="bidirectional"/>
      <node ref="U8" pin="2" pinfunction="Y0" pintype="bidirectional"/>
      <node ref="U8" pin="5" pinfunction="Z0" pintype="bidirectional"/>
      <node ref="U8" pin="6" pinfunction="INH" pintype="input"/>
      <node ref="U8" pin="8" pinfunction="VSS" pintype="power_in"/>
    </net>
    <net code="10" name="Net-(C4-Pad2)">
      <node ref="C4" pin="2" pintype="passive"/>
      <node ref="R6" pin="1" pintype="passive"/>
    </net>
    <net code="11" name="Net-(D1-K)">
      <node ref="D1" pin="1" pinfunction="K" pintype="passive"/>
      <node ref="L1" pin="1" pinfunction="1" pintype="input"/>
      <node ref="U2" pin="2" pinfunction="OUT" pintype="output"/>
    </net>
    <net code="12" name="Net-(D2-K)">
      <node ref="D2" pin="1" pinfunction="K" pintype="passive"/>
      <node ref="L2" pin="1" pinfunction="1" pintype="input"/>
      <node ref="U3" pin="2" pinfunction="OUT" pintype="output"/>
    </net>
    <net code="13" name="Net-(D3-K)">
      <node ref="D3" pin="1" pinfunction="K" pintype="passive"/>
      <node ref="R10" pin="2" pintype="passive"/>
      <node ref="R9" pin="1" pintype="passive"/>
      <node ref="U4" pin="1" pinfunction="IN_1" pintype="input"/>
    </net>
    <net code="14" name="Net-(D5-A)">
      <node ref="D5" pin="2" pinfunction="A" pintype="passive"/>
      <node ref="U6" pin="5" pinfunction="~{A}" pintype="input"/>
      <node ref="U7" pin="3" pinfunction="FRAME" pintype="output"/>
    </net>
    <net code="15" name="Net-(D5-K)">
      <node ref="D5" pin="1" pinfunction="K" pintype="passive"/>
      <node ref="R18" pin="1" pintype="passive"/>
    </net>
    <net code="16" name="Net-(D7-A)">
      <node ref="D7" pin="2" pinfunction="A" pintype="passive"/>
      <node ref="J2" pin="1" pintype="passive"/>
      <node ref="J3" pin="10" pinfunction="Pin_10" pintype="passive"/>
      <node ref="J3" pin="9" pinfunction="Pin_9" pintype="passive"/>
    </net>
    <net code="17" name="Net-(J4-PadTN)">
      <node ref="J4" pin="TN" pintype="passive"/>
      <node ref="R8" pin="2" pintype="passive"/>
    </net>
    <net code="18" name="Net-(J6-In)">
      <node ref="J5" pin="T" pintype="passive"/>
      <node ref="J6" pin="1" pinfunction="In" pintype="passive"/>
      <node ref="R4" pin="2" pintype="passive"/>
      <node ref="U1" pin="7" pintype="output"/>
    </net>
    <net code="19" name="Net-(J9-In)">
      <node ref="C24" pin="1" pintype="passive"/>
      <node ref="J8" pin="T" pintype="passive"/>
      <node ref="J9" pin="1" pinfunction="In" pintype="passive"/>
    </net>
    <net code="20" name="Net-(J10-In)">
      <node ref="J10" pin="1" pinfunction="In" pintype="passive"/>
      <node ref="R16" pin="2" pintype="passive"/>
    </net>
    <net code="21" name="Net-(R5-Pad1)">
      <node ref="R5" pin="1" pintype="passive"/>
      <node ref="R6" pin="2" pintype="passive"/>
      <node ref="U1" pin="1" pintype="output"/>
    </net>
    <net code="22" name="Net-(R11-Pad2)">
      <node ref="R11" pin="2" pintype="passive"/>
      <node ref="RV1" pin="2" pinfunction="2" pintype="passive"/>
    </net>
    <net code="23" name="Net-(R19-Pad2)">
      <node ref="R19" pin="2" pintype="passive"/>
      <node ref="RV2" pin="2" pinfunction="2" pintype="passive"/>
    </net>
    <net code="24" name="Net-(R20-Pad2)">
      <node ref="R20" pin="2" pintype="passive"/>
      <node ref="RV3" pin="2" pinfunction="2" pintype="passive"/>
    </net>
    <net code="25" name="Net-(R21-Pad2)">
      <node ref="R21" pin="2" pintype="passive"/>
      <node ref="RV4" pin="2" pinfunction="2" pintype="passive"/>
    </net>
    <net code="26" name="Net-(R22-Pad2)">
      <node ref="R22" pin="2" pintype="passive"/>
      <node ref="RV5" pin="2" pinfunction="2" pintype="passive"/>
    </net>
    <net code="27" name="Net-(U1A-+)">
      <node ref="R3" pin="1" pintype="passive"/>
      <node ref="U1" pin="3" pinfunction="+" pintype="input"/>
    </net>
    <net code="28" name="Net-(U1A--)">
      <node ref="R2" pin="1" pintype="passive"/>
      <node ref="R5" pin="2" pintype="passive"/>
      <node ref="U1" pin="2" pinfunction="-" pintype="input"/>
    </net>
    <net code="29" name="Net-(U1B--)">
      <node ref="R4" pin="1" pintype="passive"/>
      <node ref="U1" pin="6" pinfunction="-" pintype="input"/>
    </net>
    <net code="30" name="Net-(U4-FB_1)">
      <node ref="R12" pin="1" pintype="passive"/>
      <node ref="U4" pin="2" pinfunction="FB_1" pintype="input"/>
    </net>
    <net code="31" name="Net-(U4-FB_2)">
      <node ref="R13" pin="2" pintype="passive"/>
      <node ref="U4" pin="13" pinfunction="FB_2" pintype="output"/>
    </net>
    <net code="32" name="Net-(U4-V_CONTROL)">
      <node ref="R11" pin="1" pintype="passive"/>
      <node ref="U4" pin="3" pinfunction="V_CONTROL" pintype="input"/>
    </net>
    <net code="33" name="Net-(U4-V_FS)">
      <node ref="C16" pin="1" pintype="passive"/>
      <node ref="R14" pin="2" pintype="passive"/>
      <node ref="R15" pin="2" pintype="passive"/>
      <node ref="U4" pin="12" pinfunction="V_FS" pintype="input"/>
    </net>
    <net code="34" name="Net-(U4-V_OUT)">
      <node ref="R12" pin="2" pintype="passive"/>
      <node ref="R13" pin="1" pintype="passive"/>
      <node ref="R16" pin="1" pintype="passive"/>
      <node ref="U4" pin="8" pinfunction="V_OUT" pintype="output"/>
    </net>
    <net code="35" name="Net-(U5A-Cx)">
      <node ref="C19" pin="1" pintype="passive"/>
      <node ref="U5" pin="1" pinfunction="Cx" pintype="input"/>
    </net>
    <net code="36" name="Net-(U5A-Q)">
      <node ref="U5" pin="11" pinfunction="~{A}" pintype="input"/>
      <node ref="U5" pin="6" pinfunction="Q" pintype="output"/>
    </net>
    <net code="37" name="Net-(U5A-RxCx)">
      <node ref="C19" pin="2" pintype="passive"/>
      <node ref="R19" pin="1" pintype="passive"/>
      <node ref="U5" pin="2" pinfunction="RxCx" pintype="input"/>
    </net>
    <net code="38" name="Net-(U5A-~{A})">
      <node ref="U5" pin="5" pinfunction="~{A}" pintype="input"/>
      <node ref="U7" pin="1" pinfunction="CSYNC" pintype="output"/>
    </net>
    <net code="39" name="Net-(U5B-Cx)">
      <node ref="C21" pin="1" pintype="passive"/>
      <node ref="U5" pin="15" pinfunction="Cx" pintype="input"/>
    </net>
    <net code="40" name="Net-(U5B-RxCx)">
      <node ref="C21" pin="2" pintype="passive"/>
      <node ref="R21" pin="1" pintype="passive"/>
      <node ref="U5" pin="14" pinfunction="RxCx" pintype="input"/>
    </net>
    <net code="41" name="Net-(U6A-Cx)">
      <node ref="C20" pin="1" pintype="passive"/>
      <node ref="U6" pin="1" pinfunction="Cx" pintype="input"/>
    </net>
    <net code="42" name="Net-(U6A-Q)">
      <node ref="U6" pin="11" pinfunction="~{A}" pintype="input"/>
      <node ref="U6" pin="6" pinfunction="Q" pintype="output"/>
    </net>
    <net code="43" name="Net-(U6A-RxCx)">
      <node ref="C20" pin="2" pintype="passive"/>
      <node ref="R20" pin="1" pintype="passive"/>
      <node ref="U6" pin="2" pinfunction="RxCx" pintype="input"/>
    </net>
    <net code="44" name="Net-(U6B-Cx)">
      <node ref="C22" pin="1" pintype="passive"/>
      <node ref="U6" pin="15" pinfunction="Cx" pintype="input"/>
    </net>
    <net code="45" name="Net-(U6B-RxCx)">
      <node ref="C22" pin="2" pintype="passive"/>
      <node ref="R22" pin="1" pintype="passive"/>
      <node ref="U6" pin="14" pinfunction="RxCx" pintype="input"/>
    </net>
    <net code="46" name="Net-(U7-BURST)">
      <node ref="U7" pin="5" pinfunction="BURST" pintype="output"/>
      <node ref="U8" pin="10" pinfunction="B" pintype="input"/>
      <node ref="U8" pin="11" pinfunction="A" pintype="input"/>
    </net>
    <net code="47" name="Net-(U7-INT)">
      <node ref="C18" pin="1" pintype="passive"/>
      <node ref="R17" pin="1" pintype="passive"/>
      <node ref="U7" pin="6" pinfunction="INT" pintype="input"/>
    </net>
    <net code="48" name="Net-(U7-VIDEO)">
      <node ref="C17" pin="1" pintype="passive"/>
      <node ref="U7" pin="2" pinfunction="VIDEO" pintype="input"/>
    </net>
    <net code="49" name="c_blanking">
      <node ref="J11" pin="1" pinfunction="Pin_1" pintype="passive"/>
      <node ref="U5" pin="10" pinfunction="Q" pintype="output"/>
      <node ref="U8" pin="9" pinfunction="C" pintype="input"/>
    </net>
    <net code="50" name="unconnected-(J2-Pad3)">
      <node ref="J2" pin="3" pintype="passive+no_connect"/>
    </net>
    <net code="51" name="unconnected-(J3-Pin_1-Pad1)">
      <node ref="J3" pin="1" pinfunction="Pin_1" pintype="passive+no_connect"/>
    </net>
    <net code="52" name="unconnected-(J3-Pin_2-Pad2)">
      <node ref="J3" pin="2" pinfunction="Pin_2" pintype="passive+no_connect"/>
    </net>
    <net code="53" name="unconnected-(J3-Pin_11-Pad11)">
      <node ref="J3" pin="11" pinfunction="Pin_11" pintype="passive+no_connect"/>
    </net>
    <net code="54" name="unconnected-(J3-Pin_12-Pad12)">
      <node ref="J3" pin="12" pinfunction="Pin_12" pintype="passive+no_connect"/>
    </net>
    <net code="55" name="unconnected-(J3-Pin_13-Pad13)">
      <node ref="J3" pin="13" pinfunction="Pin_13" pintype="passive+no_connect"/>
    </net>
    <net code="56" name="unconnected-(J3-Pin_14-Pad14)">
      <node ref="J3" pin="14" pinfunction="Pin_14" pintype="passive+no_connect"/>
    </net>
    <net code="57" name="unconnected-(J3-Pin_15-Pad15)">
      <node ref="J3" pin="15" pinfunction="Pin_15" pintype="passive+no_connect"/>
    </net>
    <net code="58" name="unconnected-(J3-Pin_16-Pad16)">
      <node ref="J3" pin="16" pinfunction="Pin_16" pintype="passive+no_connect"/>
    </net>
    <net code="59" name="unconnected-(J5-PadTN)">
      <node ref="J5" pin="TN" pintype="passive+no_connect"/>
    </net>
    <net code="60" name="unconnected-(J8-PadTN)">
      <node ref="J8" pin="TN" pintype="passive+no_connect"/>
    </net>
    <net code="61" name="unconnected-(RV2-Pad3)">
      <node ref="RV2" pin="3" pinfunction="3" pintype="passive+no_connect"/>
    </net>
    <net code="62" name="unconnected-(RV3-Pad3)">
      <node ref="RV3" pin="3" pinfunction="3" pintype="passive+no_connect"/>
    </net>
    <net code="63" name="unconnected-(RV4-Pad3)">
      <node ref="RV4" pin="3" pinfunction="3" pintype="passive+no_connect"/>
    </net>
    <net code="64" name="unconnected-(RV5-Pad3)">
      <node ref="RV5" pin="3" pinfunction="3" pintype="passive+no_connect"/>
    </net>
    <net code="65" name="unconnected-(U4-I_c-Pad4)">
      <node ref="U4" pin="4" pinfunction="I_c" pintype="input+no_connect"/>
    </net>
    <net code="66" name="unconnected-(U4-I_fs-Pad11)">
      <node ref="U4" pin="11" pinfunction="I_fs" pintype="power_in+no_connect"/>
    </net>
    <net code="67" name="unconnected-(U4-NULL-Pad6)">
      <node ref="U4" pin="6" pinfunction="NULL" pintype="input+no_connect"/>
    </net>
    <net code="68" name="unconnected-(U5A-~{Q}-Pad7)">
      <node ref="U5" pin="7" pinfunction="~{Q}" pintype="output+no_connect"/>
    </net>
    <net code="69" name="unconnected-(U5B-~{Q}-Pad9)">
      <node ref="U5" pin="9" pinfunction="~{Q}" pintype="output+no_connect"/>
    </net>
    <net code="70" name="unconnected-(U6A-~{Q}-Pad7)">
      <node ref="U6" pin="7" pinfunction="~{Q}" pintype="output+no_connect"/>
    </net>
    <net code="71" name="unconnected-(U6B-~{Q}-Pad9)">
      <node ref="U6" pin="9" pinfunction="~{Q}" pintype="output+no_connect"/>
    </net>
    <net code="72" name="unconnected-(U7-O{slash}E-Pad7)">
      <node ref="U7" pin="7" pinfunction="O/E" pintype="output+no_connect"/>
    </net>
    <net code="73" name="unconnected-(U8-X1-Pad13)">
      <node ref="U8" pin="13" pinfunction="X1" pintype="bidirectional+no_connect"/>
    </net>
    <net code="74" name="unconnected-(U8-Y1-Pad1)">
      <node ref="U8" pin="1" pinfunction="Y1" pintype="bidirectional+no_connect"/>
    </net>
    <net code="75" name="v_blanking">
      <node ref="J11" pin="2" pinfunction="Pin_2" pintype="passive"/>
      <node ref="U5" pin="3" pinfunction="~{CD}" pintype="input"/>
      <node ref="U6" pin="10" pinfunction="Q" pintype="output"/>
    </net>
  </nets>
</export>
